{
    "id": 502,
    "events": "[{\"type\":\"cursor\",\"target\":\"Main player:tab[0]\",\"data\":{\"position\":{\"line\":9,\"ch\":15,\"sticky\":\"before\",\"xRel\":86.4375},\"selections\":[{\"anchor\":{\"line\":9,\"ch\":15,\"sticky\":\"before\",\"xRel\":86.4375},\"head\":{\"line\":9,\"ch\":15,\"sticky\":\"before\",\"xRel\":86.4375},\"goalColumn\":234.46875}]},\"delta_time\":1505.1134299999976},{\"type\":\"change\",\"target\":\"Main player:tab[0]\",\"data\":{\"from\":{\"line\":9,\"ch\":15,\"sticky\":\"before\",\"xRel\":86.4375},\"to\":{\"line\":9,\"ch\":15,\"sticky\":\"before\",\"xRel\":86.4375},\"text\":[\" \"],\"removed\":[\"\"],\"origin\":\"+input\"},\"delta_time\":1505.6581549999971},{\"type\":\"cursor\",\"target\":\"Main player:tab[0]\",\"data\":{\"position\":{\"line\":9,\"ch\":16,\"sticky\":null},\"selections\":[{\"anchor\":{\"line\":9,\"ch\":16,\"sticky\":null},\"head\":{\"line\":9,\"ch\":16,\"sticky\":null}}]},\"delta_time\":1505.658159999999},{\"type\":\"change\",\"target\":\"Main player:tab[0]\",\"data\":{\"from\":{\"line\":9,\"ch\":16,\"sticky\":null},\"to\":{\"line\":9,\"ch\":16,\"sticky\":null},\"text\":[\" \"],\"removed\":[\"\"],\"origin\":\"+input\"},\"delta_time\":1505.7859349999999},{\"type\":\"cursor\",\"target\":\"Main player:tab[0]\",\"data\":{\"position\":{\"line\":9,\"ch\":17,\"sticky\":null},\"selections\":[{\"anchor\":{\"line\":9,\"ch\":17,\"sticky\":null},\"head\":{\"line\":9,\"ch\":17,\"sticky\":null}}]},\"delta_time\":1505.785945000003},{\"type\":\"change\",\"target\":\"Main player:tab[0]\",\"data\":{\"from\":{\"line\":9,\"ch\":17,\"sticky\":null},\"to\":{\"line\":9,\"ch\":17,\"sticky\":null},\"text\":[\" \"],\"removed\":[\"\"],\"origin\":\"+input\"},\"delta_time\":1505.9300250000013},{\"type\":\"cursor\",\"target\":\"Main player:tab[0]\",\"data\":{\"position\":{\"line\":9,\"ch\":18,\"sticky\":null},\"selections\":[{\"anchor\":{\"line\":9,\"ch\":18,\"sticky\":null},\"head\":{\"line\":9,\"ch\":18,\"sticky\":null}}]},\"delta_time\":1505.9300349999976},{\"type\":\"change\",\"target\":\"Main player:tab[0]\",\"data\":{\"from\":{\"line\":9,\"ch\":18,\"sticky\":null},\"to\":{\"line\":9,\"ch\":18,\"sticky\":null},\"text\":[\" \"],\"removed\":[\"\"],\"origin\":\"+input\"},\"delta_time\":1506.0421100000021},{\"type\":\"cursor\",\"target\":\"Main player:tab[0]\",\"data\":{\"position\":{\"line\":9,\"ch\":19,\"sticky\":null},\"selections\":[{\"anchor\":{\"line\":9,\"ch\":19,\"sticky\":null},\"head\":{\"line\":9,\"ch\":19,\"sticky\":null}}]},\"delta_time\":1506.0421350000033},{\"type\":\"change\",\"target\":\"Main player:tab[0]\",\"data\":{\"from\":{\"line\":9,\"ch\":19,\"sticky\":null},\"to\":{\"line\":9,\"ch\":19,\"sticky\":null},\"text\":[\" \"],\"removed\":[\"\"],\"origin\":\"+input\"},\"delta_time\":1506.1699549999976},{\"type\":\"cursor\",\"target\":\"Main player:tab[0]\",\"data\":{\"position\":{\"line\":9,\"ch\":20,\"sticky\":null},\"selections\":[{\"anchor\":{\"line\":9,\"ch\":20,\"sticky\":null},\"head\":{\"line\":9,\"ch\":20,\"sticky\":null}}]},\"delta_time\":1506.1699650000007},{\"type\":\"change\",\"target\":\"Main player:tab[0]\",\"data\":{\"from\":{\"line\":9,\"ch\":20,\"sticky\":null},\"to\":{\"line\":9,\"ch\":20,\"sticky\":null},\"text\":[\" \"],\"removed\":[\"\"],\"origin\":\"+input\"},\"delta_time\":1506.2983450000027},{\"type\":\"cursor\",\"target\":\"Main player:tab[0]\",\"data\":{\"position\":{\"line\":9,\"ch\":21,\"sticky\":null},\"selections\":[{\"anchor\":{\"line\":9,\"ch\":21,\"sticky\":null},\"head\":{\"line\":9,\"ch\":21,\"sticky\":null}}]},\"delta_time\":1506.2983600000005},{\"type\":\"change\",\"target\":\"Main player:tab[0]\",\"data\":{\"from\":{\"line\":9,\"ch\":21,\"sticky\":null},\"to\":{\"line\":9,\"ch\":21,\"sticky\":null},\"text\":[\" \"],\"removed\":[\"\"],\"origin\":\"+input\"},\"delta_time\":1506.426180000002},{\"type\":\"cursor\",\"target\":\"Main player:tab[0]\",\"data\":{\"position\":{\"line\":9,\"ch\":22,\"sticky\":null},\"selections\":[{\"anchor\":{\"line\":9,\"ch\":22,\"sticky\":null},\"head\":{\"line\":9,\"ch\":22,\"sticky\":null}}]},\"delta_time\":1506.4261899999983},{\"type\":\"change\",\"target\":\"Main player:tab[0]\",\"data\":{\"from\":{\"line\":9,\"ch\":22,\"sticky\":null},\"to\":{\"line\":9,\"ch\":22,\"sticky\":null},\"text\":[\" \"],\"removed\":[\"\"],\"origin\":\"+input\"},\"delta_time\":1506.5381800000032},{\"type\":\"cursor\",\"target\":\"Main player:tab[0]\",\"data\":{\"position\":{\"line\":9,\"ch\":23,\"sticky\":null},\"selections\":[{\"anchor\":{\"line\":9,\"ch\":23,\"sticky\":null},\"head\":{\"line\":9,\"ch\":23,\"sticky\":null}}]},\"delta_time\":1506.5381899999993}]",
    "timestamp_offset": 1504.8683250000029,
    "duration": 3.003164999994682
}