{
    "id": 939,
    "events": "[{\"name\":\"stdin\",\"data\":\"CBtbSw==\",\"target\":\"XTerm:1\",\"delta_time\":2836.5786900000003},{\"name\":\"stdin\",\"data\":\"CBtbSw==\",\"target\":\"XTerm:1\",\"delta_time\":2836.6667100000013},{\"name\":\"stdin\",\"data\":\"Zw==\",\"target\":\"XTerm:1\",\"delta_time\":2836.794440000002},{\"name\":\"stdin\",\"data\":\"Yw==\",\"target\":\"XTerm:1\",\"delta_time\":2836.97883},{\"name\":\"stdin\",\"data\":\"Yw==\",\"target\":\"XTerm:1\",\"delta_time\":2837.1226450000013}]",
    "timestamp_offset": 2834.7212999999974,
    "duration": 3.0001149999988264
}