{
    "id": 723,
    "events": "[{\"name\":\"stdin\",\"data\":\"CA==\",\"target\":\"XTerm:1\",\"delta_time\":2181.174775000003},{\"name\":\"stdin\",\"data\":\"CA==\",\"target\":\"XTerm:1\",\"delta_time\":2181.174994999997},{\"name\":\"stdin\",\"data\":\"CA==\",\"target\":\"XTerm:1\",\"delta_time\":2181.2148199999974},{\"name\":\"stdin\",\"data\":\"CA==\",\"target\":\"XTerm:1\",\"delta_time\":2181.235559999998},{\"name\":\"stdin\",\"data\":\"CA==\",\"target\":\"XTerm:1\",\"delta_time\":2181.270285000002},{\"name\":\"stdin\",\"data\":\"G1tD\",\"target\":\"XTerm:1\",\"delta_time\":2181.616460000001},{\"name\":\"stdin\",\"data\":\"G1tD\",\"target\":\"XTerm:1\",\"delta_time\":2181.8596849999994},{\"name\":\"stdin\",\"data\":\"G1tD\",\"target\":\"XTerm:1\",\"delta_time\":2181.8937750000005},{\"name\":\"stdin\",\"data\":\"G1tD\",\"target\":\"XTerm:1\",\"delta_time\":2181.930550000001},{\"name\":\"stdin\",\"data\":\"G1tD\",\"target\":\"XTerm:1\",\"delta_time\":2181.965070000002},{\"name\":\"stdin\",\"data\":\"G1tD\",\"target\":\"XTerm:1\",\"delta_time\":2181.9980650000034},{\"name\":\"stdin\",\"data\":\"G1tD\",\"target\":\"XTerm:1\",\"delta_time\":2182.0314650000037},{\"name\":\"stdin\",\"data\":\"G1tD\",\"target\":\"XTerm:1\",\"delta_time\":2182.064710000003},{\"name\":\"stdin\",\"data\":\"G1tD\",\"target\":\"XTerm:1\",\"delta_time\":2182.0979899999984},{\"name\":\"stdin\",\"data\":\"G1tD\",\"target\":\"XTerm:1\",\"delta_time\":2182.1309399999996},{\"name\":\"stdin\",\"data\":\"G1tD\",\"target\":\"XTerm:1\",\"delta_time\":2182.164825000004},{\"name\":\"stdin\",\"data\":\"G1tD\",\"target\":\"XTerm:1\",\"delta_time\":2182.1979350000006},{\"name\":\"stdin\",\"data\":\"G1tD\",\"target\":\"XTerm:1\",\"delta_time\":2182.289325000001},{\"name\":\"stdin\",\"data\":\"CA==\",\"target\":\"XTerm:1\",\"delta_time\":2182.9971449999975},{\"name\":\"stdin\",\"data\":\"CA==\",\"target\":\"XTerm:1\",\"delta_time\":2183.2478850000007},{\"name\":\"stdin\",\"data\":\"CA==\",\"target\":\"XTerm:1\",\"delta_time\":2183.278070000004},{\"name\":\"stdin\",\"data\":\"CA==\",\"target\":\"XTerm:1\",\"delta_time\":2183.3113850000045},{\"name\":\"stdin\",\"data\":\"CA==\",\"target\":\"XTerm:1\",\"delta_time\":2183.3456449999976},{\"name\":\"stdin\",\"data\":\"CA==\",\"target\":\"XTerm:1\",\"delta_time\":2183.381295000003},{\"name\":\"stdin\",\"data\":\"CA==\",\"target\":\"XTerm:1\",\"delta_time\":2183.4163950000043},{\"name\":\"stdin\",\"data\":\"CA==\",\"target\":\"XTerm:1\",\"delta_time\":2183.4491949999974},{\"name\":\"stdin\",\"data\":\"CA==\",\"target\":\"XTerm:1\",\"delta_time\":2183.4834000000014},{\"name\":\"stdin\",\"data\":\"CA==\",\"target\":\"XTerm:1\",\"delta_time\":2183.5176349999997},{\"name\":\"stdin\",\"data\":\"CA==\",\"target\":\"XTerm:1\",\"delta_time\":2183.5520100000035},{\"name\":\"stdin\",\"data\":\"CA==\",\"target\":\"XTerm:1\",\"delta_time\":2183.586209999998},{\"name\":\"stdin\",\"data\":\"CA==\",\"target\":\"XTerm:1\",\"delta_time\":2183.620599999999},{\"name\":\"stdin\",\"data\":\"CA==\",\"target\":\"XTerm:1\",\"delta_time\":2183.654870000002},{\"name\":\"stdin\",\"data\":\"G1tB\",\"target\":\"XTerm:1\",\"delta_time\":2183.8406750000036}]",
    "timestamp_offset": 2181.1276000000043,
    "duration": 3.020870000000112
}